  {
	"crops": {
		"WR": {
			"cropParams": {
				"species": ["include-from-file", "monica-parameters/crops/rye.json"],
				"cultivar": ["include-from-file", "monica-parameters/crops/rye/winter rye.json"]
			},
			"residueParams": ["include-from-file", "monica-parameters/crop-residues/rye.json"]
		},
		"SM": {
			"cropParams": {
				"species": ["include-from-file", "monica-parameters/crops/maize.json"],
				"cultivar": ["include-from-file", "monica-parameters/crops/maize/silage maize.json"]
			},
			"residueParams": ["include-from-file", "monica-parameters/crop-residues/maize.json"]
		},
		"WW": {
			"cropParams": {
				"species": ["include-from-file", "monica-parameters/crops/wheat.json"],
				"cultivar": ["include-from-file", "monica-parameters/crops/wheat/winter wheat.json"]
			},
			"residueParams": ["include-from-file", "monica-parameters/crop-residues/wheat.json"]
		},
		"WB": {
			"cropParams": {
				"species": ["include-from-file", "monica-parameters/crops/barley.json"],
				"cultivar": ["include-from-file", "monica-parameters/crops/barley/winter barley.json"]
			},
			"residueParams": ["include-from-file", "monica-parameters/crop-residues/barley.json"]
		},
		"SB": {
			"cropParams": {
				"species": ["include-from-file", "monica-parameters/crops/barley.json"],
				"cultivar": ["include-from-file", "monica-parameters/crops/barley/spring barley.json"]
			},
			"residueParams": ["include-from-file", "monica-parameters/crop-residues/barley.json"]
		},
		"WRa": {
			"cropParams": {
				"species": ["include-from-file", "monica-parameters/crops/rape.json"],
				"cultivar": ["include-from-file", "monica-parameters/crops/rape/winter rape.json"]
			},
			"residueParams": ["include-from-file", "monica-parameters/crop-residues/rape.json"]
		},
		"PH": {			
			"cropParams": {
				"species": ["include-from-file", "monica-parameters/crops/phacelia.json"],
				"cultivar": ["include-from-file", "monica-parameters/crops/phacelia/.json"]
			},			
			"residueParams": ["include-from-file", "monica-parameters/crop-residues/phacelia/cover.json"]
		},
		"PO": {			
			"cropParams": {
				"species": ["include-from-file", "monica-parameters/crops/potato.json"],
				"cultivar": ["include-from-file", "monica-parameters/crops/potato/moderately early potato.json"]
			},			
			"residueParams": ["include-from-file", "monica-parameters/crop-residues/potato.json"]
		},
		"SBee": {			
			"cropParams": {
				"species": ["include-from-file", "monica-parameters/crops/sugar beet.json"],
				"cultivar": ["include-from-file", "monica-parameters/crops/sugar beet/.json"]
			},			
			"residueParams": ["include-from-file", "monica-parameters/crop-residues/beet.json"]
		},
		"WTr": {			
			"cropParams": {
				"species": ["include-from-file", "monica-parameters/crops/triticale.json"],
				"cultivar": ["include-from-file", "monica-parameters/crops/triticale/winter triticale.json"]
			},			
			"residueParams": ["include-from-file", "monica-parameters/crop-residues/triticale.json"]
		},
		"GM": {			
			"cropParams": {
				"species": ["include-from-file", "monica-parameters/crops/maize.json"],
				"cultivar": ["include-from-file", "monica-parameters/crops/maize/grain maize.json"]
			},			
			"residueParams": ["include-from-file", "monica-parameters/crop-residues/maize.json"]
		}
	},
	
	"fert-params": {
		"AN": ["include-from-file", "monica-parameters/mineral-fertilisers/AN.json"],
		"CADLM": ["include-from-file", "monica-parameters/organic-fertilisers/CADLM.json"]
	}, 	

	"cropRotation": [
		
	],	
	

	"CropParameters": {
		"DEFAULT": ["include-from-file", "monica-parameters/user-parameters/hermes-crop.json"]
	}
}
